LICENSE.txt
MANIFEST.in
README.rst
setup.py
django_nosqladmin.egg-info/PKG-INFO
django_nosqladmin.egg-info/SOURCES.txt
django_nosqladmin.egg-info/dependency_links.txt
django_nosqladmin.egg-info/not-zip-safe
django_nosqladmin.egg-info/requires.txt
django_nosqladmin.egg-info/top_level.txt
nosqladmin/__init__.py
nosqladmin/models.py
nosqladmin/tests.py
nosqladmin/urls.py
nosqladmin/views.py