Metadata-Version: 1.0
Name: django-nosqladmin
Version: 0.1.1
Summary: An introspective interface for Django and Document Based NoSQL databases
Home-page: http://github.com/pydanny/django-nosqladmin
Author: Daniel Greenfeld
Author-email: pydanny@gmail.com
License: MIT
Keywords: mongodb,django,nosql
Platform: UNKNOWN
Classifier: Development Status :: 3 - Alpha
Classifier: Environment :: Web Environment
Classifier: Framework :: Django
Classifier: License :: OSI Approved :: BSD License
Classifier: Operating System :: OS Independent
Classifier: Programming Language :: JavaScript
Classifier: Programming Language :: Python :: 2.6
Classifier: Programming Language :: Python :: 2.7
Classifier: Topic :: Internet :: WWW/HTTP
Classifier: Topic :: Internet :: WWW/HTTP :: Dynamic Content
Classifier: Topic :: Software Development :: Libraries :: Python Modules
